Metadata-Version: 1.1
Name: SyGMa
Version: 1.0.1
Summary: Systematic Generation of potential MetAbolites
Home-page: https://github.com/ridderl/sygma
Author: Lars Ridder
Author-email: lars.ridder@esciencecenter.nl>
License: GPL
Platform: UNKNOWN
Classifier: Intended Audience :: Science/Research
Classifier: Environment :: Console
Classifier: Natural Language :: English
Classifier: Operating System :: OS Independent
Classifier: Topic :: Scientific/Engineering :: Chemistry
Classifier: Programming Language :: Python :: 2.7
